digenpyweb
