Metadata-Version: 1.1
Name: DigenpyWeb
Version: 0.0.1
Summary: Digenpy Web interface
Home-page: http://www.digenpy.com/
Author: UNKNOWN
Author-email: UNKNOWN
License: GPL2
Download-URL: http://www.digenpy.com
Platform: UNKNOWN
Classifier: Development Status :: 4 - Beta
Requires: Digenpy
